myhydra/__init__.py
myhydra-0.5.dist-info/LICENSE.txt
myhydra-0.5.dist-info/METADATA
myhydra-0.5.dist-info/WHEEL
myhydra-0.5.dist-info/top_level.txt
myhydra-0.5.dist-info/RECORD
